LICENSE
MANIFEST.in
README.rst
setup.py
boosterpacks/__init__.py
boosterpacks/booster_choice.py
boosterpacks.egg-info/PKG-INFO
boosterpacks.egg-info/SOURCES.txt
boosterpacks.egg-info/dependency_links.txt
boosterpacks.egg-info/not-zip-safe
boosterpacks.egg-info/top_level.txt