Metadata-Version: 1.0
Name: boosterpacks
Version: 0.1.1
Summary: Simple of boosterpack in Star Crusade
Home-page: UNKNOWN
Author: Andrew Grinevich
Author-email: andrew.grinevich@gmail.com
License: MIT
Platform: UNKNOWN
